missinglink/__init__.py
missinglink/sdk/__init__.py
missinglink/sdk/conda_util.py
missinglink/sdk/pip_util.py
missinglink/sdk/pkg_provider.py
missinglink/sdk/print_or_log.py
missinglink_kernel/__init__.py
missinglink_kernel/inplace_version.py
missinglink_kernel/callback/__init__.py
missinglink_kernel/callback/api_get_resources.py
missinglink_kernel/callback/auth_params.py
missinglink_kernel/callback/base_callback.py
missinglink_kernel/callback/base_callback_images.py
missinglink_kernel/callback/data_generator_factory.py
missinglink_kernel/callback/exceptions.py
missinglink_kernel/callback/interfaces.py
missinglink_kernel/callback/keras_callback.py
missinglink_kernel/callback/log_monitor.py
missinglink_kernel/callback/logger_wrapper.py
missinglink_kernel/callback/ml_env_vars.py
missinglink_kernel/callback/monkey_patch_process.py
missinglink_kernel/callback/phase.py
missinglink_kernel/callback/pycaffe_callback.py
missinglink_kernel/callback/pytorch_project.py
missinglink_kernel/callback/queries.py
missinglink_kernel/callback/remote_logger.py
missinglink_kernel/callback/root_logger_sniffer.py
missinglink_kernel/callback/settings.py
missinglink_kernel/callback/sklearn_project.py
missinglink_kernel/callback/state_counter.py
missinglink_kernel/callback/tensorflow_hooks.py
missinglink_kernel/callback/tensorflow_patch_session.py
missinglink_kernel/callback/tensorflow_project.py
missinglink_kernel/callback/test_reports_saver.py
missinglink_kernel/callback/trie.py
missinglink_kernel/callback/vanilla_project.py
missinglink_kernel/callback/dispatchers/__init__.py
missinglink_kernel/callback/dispatchers/json_encoder.py
missinglink_kernel/callback/dispatchers/missinglink.py
missinglink_kernel/callback/utilities/__init__.py
missinglink_kernel/callback/utilities/socket_utils.py
missinglink_kernel/callback/utilities/source_tracking.py
missinglink_kernel/callback/utilities/utils.py
missinglink_kernel/callback/vis/__init__.py
missinglink_kernel/callback/vis/dynamic_import.py
missinglink_kernel-19.9.26893.dist-info/LICENSE
missinglink_kernel-19.9.26893.dist-info/METADATA
missinglink_kernel-19.9.26893.dist-info/WHEEL
missinglink_kernel-19.9.26893.dist-info/top_level.txt
missinglink_kernel-19.9.26893.dist-info/RECORD
