Metadata-Version: 2.1
Name: missinglink-kernel
Version: 19.9.26893
Summary: Kernel SDK for streaming realtime metrics to https://missinglink.ai
Home-page: UNKNOWN
Author: MissingLink.ai
Author-email: support+sdk@missinglink.ai
License: mit
Keywords: prod
Platform: any
Requires-Dist: protobuf (>=3.2.0)
Requires-Dist: gitpython (<2.2,>=2.1.9)
Requires-Dist: retrying (>=1.3.3)
Requires-Dist: numpy
Requires-Dist: six
Requires-Dist: requests
Requires-Dist: ml-legit (>=19.9.8623)
Requires-Dist: ml-core (>=19.9.3925)
Requires-Dist: wcwidth (>=0.1.7)
Requires-Dist: Pygments (>=2.2.0)
Requires-Dist: urllib3 (<1.25,>=1.21.1)
Requires-Dist: lockfile (>=0.12.2)
Requires-Dist: contextlib2 ; python_version < '3.0'
Requires-Dist: psutil (>=5.6.2) ; sys_platform == 'win32'
